orchestr8/__init__.py
orchestr8/cli.py
orchestr8/exceptions.py
orchestr8/sdk.py
orchestr8/auth/__init__.py
orchestr8/auth/github_oauth.py
orchestr8/auth/keycloak_idp.py
orchestr8/cli/module.py
orchestr8/commands/argocd.py
orchestr8/commands/bootstrap.py
orchestr8/commands/branch.py
orchestr8/commands/doctor.py
orchestr8/commands/llama.py
orchestr8/commands/module.py
orchestr8/commands/secrets.py
orchestr8/commands/tenant.py
orchestr8/core/__init__.py
orchestr8/core/config.py
orchestr8/core/cue_engine.py
orchestr8/core/orchestrator.py
orchestr8/core/secrets.py
orchestr8/core/terraform.py
orchestr8/core/validator.py
orchestr8/providers/__init__.py
orchestr8/providers/aws.py
orchestr8/providers/azure.py
orchestr8/providers/github.py
orchestr8/providers/local.py
orchestr8/utils/azure_cli.py
orchestr8_platform-3.3.1.dist-info/METADATA
orchestr8_platform-3.3.1.dist-info/WHEEL
orchestr8_platform-3.3.1.dist-info/entry_points.txt
orchestr8_platform-3.3.1.dist-info/top_level.txt
orchestr8_platform-3.3.1.dist-info/RECORD
